README.md
setup.cfg
setup.py
collibra_catalog/__init__.py
collibra_catalog/api_client.py
collibra_catalog/configuration.py
collibra_catalog/exceptions.py
collibra_catalog/rest.py
collibra_catalog.egg-info/PKG-INFO
collibra_catalog.egg-info/SOURCES.txt
collibra_catalog.egg-info/dependency_links.txt
collibra_catalog.egg-info/requires.txt
collibra_catalog.egg-info/top_level.txt
collibra_catalog/api/__init__.py
collibra_catalog/api/jdbc_schema_ingestion_api.py
collibra_catalog/api/job_server_instance_configuration_api.py
collibra_catalog/api/marketplace_accounting_api.py
collibra_catalog/api/profiling_api.py
collibra_catalog/api/s3_api.py
collibra_catalog/models/__init__.py
collibra_catalog/models/add_crawler_request.py
collibra_catalog/models/add_s3_schedule_request.py
collibra_catalog/models/add_schema_from_jdbc_request.py
collibra_catalog/models/asset_identifier.py
collibra_catalog/models/categorical_metadata.py
collibra_catalog/models/change_s3_schedule_request.py
collibra_catalog/models/column_profile.py
collibra_catalog/models/counts.py
collibra_catalog/models/crawler.py
collibra_catalog/models/crawler_include_path.py
collibra_catalog/models/crawler_include_path_request.py
collibra_catalog/models/data_profiling_request.py
collibra_catalog/models/data_profiling_response.py
collibra_catalog/models/database_metadata.py
collibra_catalog/models/distributions.py
collibra_catalog/models/histogram_bin.py
collibra_catalog/models/job.py
collibra_catalog/models/job_server_instance.py
collibra_catalog/models/job_server_instance_response.py
collibra_catalog/models/paged_response_job_server_instance.py
collibra_catalog/models/point.py
collibra_catalog/models/quantiles.py
collibra_catalog/models/refresh_jdbc_schema_request.py
collibra_catalog/models/remove_crawler_request.py
collibra_catalog/models/s3_schedule.py
collibra_catalog/models/samples.py
collibra_catalog/models/statistics.py
collibra_catalog/models/update_crawler_request.py
test/test_add_crawler_request.py
test/test_add_s3_schedule_request.py
test/test_add_schema_from_jdbc_request.py
test/test_asset_identifier.py
test/test_categorical_metadata.py
test/test_change_s3_schedule_request.py
test/test_column_profile.py
