Metadata-Version: 1.0
Name: collibra-catalog
Version: 1.0.0
Summary: Collibra Catalog API
Home-page: UNKNOWN
Author: OpenAPI Generator community
Author-email: team@openapitools.org
License: UNKNOWN
Keywords: OpenAPI,OpenAPI-Generator,Collibra Catalog API
Platform: UNKNOWN
